hand_gesture/__init__.py
hand_gesture/config.py
hand_gesture/engine.py
hand_gesture/gestures.py
hand_gesture/logging_config.py
hand_gesture/recognizer.py
hand_gesture/stabilizer.py
hand_gesture/tracker.py
hand_gesture/utils.py
hand_gesture/assets/__init__.py
hand_gesture_engine-0.1.1.dist-info/METADATA
hand_gesture_engine-0.1.1.dist-info/WHEEL
hand_gesture_engine-0.1.1.dist-info/top_level.txt
hand_gesture_engine-0.1.1.dist-info/RECORD
