Metadata-Version: 2.1
Name: hand-gesture-engine
Version: 0.1.1
Summary: A lightweight hand gesture recognition engine
Home-page: https://github.com/KaranVishwakarma-1807/hand-gesture-engine
Author: Karan Vishwakarma
Author-email: vishwakarmakaran625@gmail.com
Classifier: Programming Language :: Python :: 3
Classifier: License :: OSI Approved :: MIT License
Classifier: Operating System :: OS Independent
Requires-Python: >=3.9
Requires-Dist: opencv-python
Requires-Dist: mediapipe
Requires-Dist: numpy
